text_cleaning_gangadhar/__init__.py
text_cleaning_gangadhar/textclean.py
text_cleaning_gangadhar-0.0.1.dist-info/LICENSE
text_cleaning_gangadhar-0.0.1.dist-info/METADATA
text_cleaning_gangadhar-0.0.1.dist-info/WHEEL
text_cleaning_gangadhar-0.0.1.dist-info/top_level.txt
text_cleaning_gangadhar-0.0.1.dist-info/RECORD
